<?xml version="1.0" encoding="utf-8"?>
	<annotation>
		<folder>driving_annotation_dataset</folder>
		<filename>AUAU040101.jpg</filename>
		<size>
			<width>640</width>
			<height>640</height>
			<depth>3</depth>
		</size>
		<object>
			<name>AFV</name>
			<pose>Unspecified</pose>
			<truncated>0</truncated>
			<difficult>0</difficult>
			<bndbox>
				<xmin>184</xmin>
				<ymin>177</ymin>
				<xmax>313</xmax>
				<ymax>262</ymax>
			</bndbox>
		</object>
		<object>
			<name>AFV</name>
			<pose>Unspecified</pose>
			<truncated>0</truncated>
			<difficult>0</difficult>
			<bndbox>
				<xmin>147</xmin>
				<ymin>91</ymin>
				<xmax>274</xmax>
				<ymax>182</ymax>
			</bndbox>
		</object>
	</annotation>
