<?xml version="1.0" encoding="utf-8"?>
	<annotation>
		<folder>driving_annotation_dataset</folder>
		<filename>AUAU030652.jpg</filename>
		<size>
			<width>640</width>
			<height>640</height>
			<depth>3</depth>
		</size>
		<object>
			<name>CV</name>
			<pose>Unspecified</pose>
			<truncated>0</truncated>
			<difficult>0</difficult>
			<bndbox>
				<xmin>1</xmin>
				<ymin>456</ymin>
				<xmax>21</xmax>
				<ymax>498</ymax>
			</bndbox>
		</object>
		<object>
			<name>CV</name>
			<pose>Unspecified</pose>
			<truncated>0</truncated>
			<difficult>0</difficult>
			<bndbox>
				<xmin>546</xmin>
				<ymin>224</ymin>
				<xmax>588</xmax>
				<ymax>262</ymax>
			</bndbox>
		</object>
		<object>
			<name>CV</name>
			<pose>Unspecified</pose>
			<truncated>0</truncated>
			<difficult>0</difficult>
			<bndbox>
				<xmin>621</xmin>
				<ymin>433</ymin>
				<xmax>639</xmax>
				<ymax>473</ymax>
			</bndbox>
		</object>
		<object>
			<name>CV</name>
			<pose>Unspecified</pose>
			<truncated>0</truncated>
			<difficult>0</difficult>
			<bndbox>
				<xmin>530</xmin>
				<ymin>586</ymin>
				<xmax>576</xmax>
				<ymax>622</ymax>
			</bndbox>
		</object>
		<object>
			<name>CV</name>
			<pose>Unspecified</pose>
			<truncated>0</truncated>
			<difficult>0</difficult>
			<bndbox>
				<xmin>542</xmin>
				<ymin>622</ymin>
				<xmax>584</xmax>
				<ymax>640</ymax>
			</bndbox>
		</object>
		<object>
			<name>CV</name>
			<pose>Unspecified</pose>
			<truncated>0</truncated>
			<difficult>0</difficult>
			<bndbox>
				<xmin>80</xmin>
				<ymin>617</ymin>
				<xmax>112</xmax>
				<ymax>641</ymax>
			</bndbox>
		</object>
	</annotation>
