<?xml version="1.0" encoding="utf-8"?>
	<annotation>
		<folder>driving_annotation_dataset</folder>
		<filename>RURU010038.jpg</filename>
		<size>
			<width>640</width>
			<height>640</height>
			<depth>3</depth>
		</size>
		<object>
			<name>AFV</name>
			<pose>Unspecified</pose>
			<truncated>0</truncated>
			<difficult>0</difficult>
			<bndbox>
				<xmin>482</xmin>
				<ymin>251</ymin>
				<xmax>602</xmax>
				<ymax>311</ymax>
			</bndbox>
		</object>
		<object>
			<name>SMV</name>
			<pose>Unspecified</pose>
			<truncated>0</truncated>
			<difficult>0</difficult>
			<bndbox>
				<xmin>425</xmin>
				<ymin>69</ymin>
				<xmax>480</xmax>
				<ymax>101</ymax>
			</bndbox>
		</object>
		<object>
			<name>AFV</name>
			<pose>Unspecified</pose>
			<truncated>0</truncated>
			<difficult>0</difficult>
			<bndbox>
				<xmin>502</xmin>
				<ymin>303</ymin>
				<xmax>603</xmax>
				<ymax>367</ymax>
			</bndbox>
		</object>
	</annotation>
