<?xml version="1.0" encoding="utf-8"?>
	<annotation>
		<folder>driving_annotation_dataset</folder>
		<filename>RURU020237.jpg</filename>
		<size>
			<width>640</width>
			<height>640</height>
			<depth>3</depth>
		</size>
		<object>
			<name>AFV</name>
			<pose>Unspecified</pose>
			<truncated>0</truncated>
			<difficult>0</difficult>
			<bndbox>
				<xmin>262</xmin>
				<ymin>145</ymin>
				<xmax>370</xmax>
				<ymax>244</ymax>
			</bndbox>
		</object>
		<object>
			<name>AFV</name>
			<pose>Unspecified</pose>
			<truncated>0</truncated>
			<difficult>0</difficult>
			<bndbox>
				<xmin>190</xmin>
				<ymin>293</ymin>
				<xmax>290</xmax>
				<ymax>379</ymax>
			</bndbox>
		</object>
		<object>
			<name>AFV</name>
			<pose>Unspecified</pose>
			<truncated>0</truncated>
			<difficult>0</difficult>
			<bndbox>
				<xmin>145</xmin>
				<ymin>336</ymin>
				<xmax>250</xmax>
				<ymax>419</ymax>
			</bndbox>
		</object>
		<object>
			<name>AFV</name>
			<pose>Unspecified</pose>
			<truncated>0</truncated>
			<difficult>0</difficult>
			<bndbox>
				<xmin>116</xmin>
				<ymin>410</ymin>
				<xmax>217</xmax>
				<ymax>508</ymax>
			</bndbox>
		</object>
		<object>
			<name>AFV</name>
			<pose>Unspecified</pose>
			<truncated>0</truncated>
			<difficult>0</difficult>
			<bndbox>
				<xmin>74</xmin>
				<ymin>485</ymin>
				<xmax>176</xmax>
				<ymax>584</ymax>
			</bndbox>
		</object>
		<object>
			<name>AFV</name>
			<pose>Unspecified</pose>
			<truncated>0</truncated>
			<difficult>0</difficult>
			<bndbox>
				<xmin>214</xmin>
				<ymin>216</ymin>
				<xmax>324</xmax>
				<ymax>305</ymax>
			</bndbox>
		</object>
	</annotation>
